tic_tac_taco_pizza.py
tic_tac_taco_pizza-0.1.2.dist-info/entry_points.txt
tic_tac_taco_pizza-0.1.2.dist-info/LICENSE
tic_tac_taco_pizza-0.1.2.dist-info/WHEEL
tic_tac_taco_pizza-0.1.2.dist-info/METADATA
tic_tac_taco_pizza-0.1.2.dist-info/RECORD
