Metadata-Version: 1.2
Name: tic_tac_taco_pizza
Version: 0.1.2
Summary: Play tic tac toe with taco 🌮 and pizza 🍕
Home-page: https://github.com/Mariatta/tic_tac_taco_pizza
License: UNKNOWN
Author: Mariatta Wijaya
Author-email: mariatta.wijaya@gmail.com
Maintainer: Mariatta Wijaya
Maintainer-email: mariatta.wijaya@gmail.com
Requires-Python: >=3.6
Classifier: Programming Language :: Python :: 3.6
Classifier: Intended Audience :: Developers
Classifier: License :: OSI Approved :: Apache Software License
Requires-Dist: click~=6.7
